{"nodes": [{"id": "times_pos_logo", "label": "TIMES POS Logo", "file_type": "image", "source_file": "icons/logo_web3_192.png", "source_location": null, "source_url": null, "captured_at": null, "author": null, "contributor": null}, {"id": "times_pos_app", "label": "TIMES POS Application", "file_type": "image", "source_file": "icons/logo_web3_192.png", "source_location": null, "source_url": null, "captured_at": null, "author": null, "contributor": null}, {"id": "user_avatar_icon", "label": "User Avatar Icon", "file_type": "image", "source_file": "icons/logo_web3_192.png", "source_location": null, "source_url": null, "captured_at": null, "author": null, "contributor": null}, {"id": "orange_gradient_style", "label": "Orange Gradient Visual Style", "file_type": "image", "source_file": "icons/logo_web3_192.png", "source_location": null, "source_url": null, "captured_at": null, "author": null, "contributor": null}, {"id": "web_app_icon", "label": "Web Application Icon (192px)", "file_type": "image", "source_file": "icons/logo_web3_192.png", "source_location": null, "source_url": null, "captured_at": null, "author": null, "contributor": null}], "edges": [{"source": "times_pos_logo", "target": "times_pos_app", "relation": "is_brand_identity_of", "confidence": "EXTRACTED", "confidence_score": 1.0, "source_file": "icons/logo_web3_192.png", "source_location": null, "weight": 1.0}, {"source": "times_pos_logo", "target": "user_avatar_icon", "relation": "uses_design_motif", "confidence": "EXTRACTED", "confidence_score": 1.0, "source_file": "icons/logo_web3_192.png", "source_location": null, "weight": 1.0}, {"source": "times_pos_logo", "target": "orange_gradient_style", "relation": "uses_visual_style", "confidence": "EXTRACTED", "confidence_score": 1.0, "source_file": "icons/logo_web3_192.png", "source_location": null, "weight": 1.0}, {"source": "times_pos_logo", "target": "web_app_icon", "relation": "is_used_as", "confidence": "EXTRACTED", "confidence_score": 1.0, "source_file": "icons/logo_web3_192.png", "source_location": null, "weight": 1.0}, {"source": "user_avatar_icon", "target": "times_pos_app", "relation": "represents_user_focus_of", "confidence": "INFERRED", "confidence_score": 0.75, "source_file": "icons/logo_web3_192.png", "source_location": null, "weight": 0.75}, {"source": "orange_gradient_style", "target": "times_pos_app", "relation": "defines_brand_color_of", "confidence": "INFERRED", "confidence_score": 0.85, "source_file": "icons/logo_web3_192.png", "source_location": null, "weight": 0.85}, {"source": "web_app_icon", "target": "times_pos_app", "relation": "provides_pwa_icon_for", "confidence": "INFERRED", "confidence_score": 0.95, "source_file": "icons/logo_web3_192.png", "source_location": null, "weight": 0.95}], "hyperedges": []}